[
  {
    "productNameClean": "Pulverizador Snow Foam manual 2L Com 2 Bicos Para Carros+2...",
    "imageUrl": "https://cf.shopee.com.br/file/cn-11134207-820l4-mlycmqcyt81w64",
    "ratingStar": "4.8",
    "priceDiscountRate": 54,
    "price": "37.9",
    "sales": 830,
    "offerLink": "https://s.shopee.com.br/70FhUqGNhH",
    "nicho": "Ferramentas",
    "timestamp": 1774523207
  },
  {
    "productNameClean": "Lavadora de Alta Pressão Sem Fio Portátil Recarregável Carros...",
    "imageUrl": "https://cf.shopee.com.br/file/br-11134207-7r98o-mdagm6f5sni9d0",
    "ratingStar": "4.8",
    "priceDiscountRate": 35,
    "price": "94.8",
    "sales": 1115,
    "offerLink": "https://s.shopee.com.br/3fzFXx6las",
    "nicho": "Ferramentas",
    "timestamp": 1774524285
  },
  {
    "productNameClean": "Parafusadeira Portátil Sem Fio 45 Peças Chaves Fenda Broca Philips...",
    "imageUrl": "https://cf.shopee.com.br/file/br-11134207-7r98o-mayfw33oi0en50",
    "ratingStar": "4.8",
    "priceDiscountRate": 53,
    "price": "37.89",
    "sales": 1568,
    "offerLink": "https://s.shopee.com.br/40c5wyd3Kc",
    "nicho": "Ferramentas",
    "timestamp": 1774524645
  },
  {
    "productNameClean": "Aspirador de Pó Doméstico 3 em 1 Sem Fio Limpeza...",
    "imageUrl": "https://cf.shopee.com.br/file/br-11134207-81ztc-mkcjoatoypz734",
    "ratingStar": "4.5",
    "priceDiscountRate": 39,
    "price": "72.99",
    "sales": 330,
    "offerLink": "https://s.shopee.com.br/W2DnMwApi",
    "nicho": "Ferramentas",
    "timestamp": 1774525366
  },
  {
    "productNameClean": "Esmerilhadeira Lixadeira Angular Profissional 900w 115mm Com 3 Discos",
    "imageUrl": "https://cf.shopee.com.br/file/br-11134207-820m7-mlhotdf9q8sm99",
    "ratingStar": "4.9",
    "priceDiscountRate": 52,
    "price": "125",
    "sales": 327,
    "offerLink": "https://s.shopee.com.br/6VJQwo7EMC",
    "nicho": "Ferramentas",
    "timestamp": 1774525725
  },
  {
    "productNameClean": "Canivete Muito Afiado Retrátil Automático Militar",
    "imageUrl": "https://cf.shopee.com.br/file/br-11134207-7r98o-lwslsycpg4tyec",
    "ratingStar": "4.7",
    "priceDiscountRate": 34,
    "price": "21.9",
    "sales": 181,
    "offerLink": "https://s.shopee.com.br/4LEwOTR4aH",
    "nicho": "Ferramentas",
    "timestamp": 1774527165
  },
  {
    "productNameClean": "Kit Serra Adaptador de Serra Tico-Tico Elétrica para Furadeira...",
    "imageUrl": "https://cf.shopee.com.br/file/sg-11134201-7rdvn-mdqyys6nkcfw98",
    "ratingStar": "4.7",
    "priceDiscountRate": 57,
    "price": "25.78",
    "sales": 571,
    "offerLink": "https://s.shopee.com.br/4AvWCzXqdL",
    "nicho": "Ferramentas",
    "timestamp": 1774527885
  },
  {
    "productNameClean": "Snow Pump 3 Em 1 Pulverizador Manual 2L Snow Foam...",
    "imageUrl": "https://cf.shopee.com.br/file/br-11134207-81z1k-mi4hhkklaj2a74",
    "ratingStar": "4.9",
    "priceDiscountRate": 16,
    "price": "40.9",
    "sales": 704,
    "offerLink": "https://s.shopee.com.br/5q3kDI4r3k",
    "nicho": "Ferramentas",
    "timestamp": 1774528965
  },
  {
    "productNameClean": "110V/220V Máquina De Solda Inversora MMA-200 Tecnologia IGBT Ferramenta...",
    "imageUrl": "https://cf.shopee.com.br/file/cn-11134207-820l4-mk0cbu93vx1f01",
    "ratingStar": "4.9",
    "priceDiscountRate": 52,
    "price": "269",
    "sales": 871,
    "offerLink": "https://s.shopee.com.br/2qQ8eBoAqm",
    "nicho": "Ferramentas",
    "timestamp": 1774529325
  },
  {
    "productNameClean": "Bolsa Mala Esportiva Mochila Costa Transversal Fitness Treino Futebol Academia...",
    "imageUrl": "https://cf.shopee.com.br/file/sg-11134201-7rbk0-lkrcqtwv575292",
    "ratingStar": "4.8",
    "priceDiscountRate": 61,
    "price": "38.55",
    "sales": 549,
    "offerLink": "https://s.shopee.com.br/40c62kHyV4",
    "nicho": "Ferramentas",
    "timestamp": 1774529685
  },
  {
    "productNameClean": "Mochila de Emergência 80 itens Kit sobrevivência EDC Primeiros Socorros...",
    "imageUrl": "https://cf.shopee.com.br/file/br-11134207-7r98o-m2lptnt24x6tf5",
    "ratingStar": "4.8",
    "priceDiscountRate": 30,
    "price": "165.9",
    "sales": 285,
    "offerLink": "https://s.shopee.com.br/4qBD3Vs9dM",
    "nicho": "Ferramentas",
    "timestamp": 1774530765
  },
  {
    "productNameClean": "Furadeira Parafusadeira 48V Kit Profissional Sem Fio Com Maleta...",
    "imageUrl": "https://cf.shopee.com.br/file/sg-11134201-822zz-mhwy80fhyqkg86",
    "ratingStar": "4.9",
    "priceDiscountRate": 72,
    "price": "149.99",
    "sales": 2664,
    "offerLink": "https://s.shopee.com.br/AUpZoL4pB9",
    "nicho": "Ferramentas",
    "timestamp": 1774531125
  },
  {
    "productNameClean": "Kit Ferro De Solda Soldar Soldador 60w + Estranho",
    "imageUrl": "https://cf.shopee.com.br/file/sg-11134201-7rfi8-m36ro5dvw6cn02",
    "ratingStar": "4.6",
    "priceDiscountRate": 15,
    "price": "25.5",
    "sales": 454,
    "offerLink": "https://s.shopee.com.br/2LTs5k7oPu",
    "nicho": "Ferramentas",
    "timestamp": 1774531485
  },
  {
    "productNameClean": "Bico Desentupidor De Tubulação Para Lavadora De Alta Pressão",
    "imageUrl": "https://cf.shopee.com.br/file/br-11134207-7r98o-mbq3djp896efc3",
    "ratingStar": "4.8",
    "priceDiscountRate": 10,
    "price": "29.9",
    "sales": 440,
    "offerLink": "https://s.shopee.com.br/7fVORxL40Q",
    "nicho": "Ferramentas",
    "timestamp": 1774531845
  },
  {
    "productNameClean": "Cesto De Roupa Suja Dobrável Organizador 3 Compartimentos",
    "imageUrl": "https://cf.shopee.com.br/file/sg-11134201-7rce7-m6be8291hkuicf",
    "ratingStar": "4.9",
    "priceDiscountRate": 43,
    "price": "79.99",
    "sales": 650,
    "offerLink": "https://s.shopee.com.br/7AZ7rRunRf",
    "nicho": "Ferramentas",
    "timestamp": 1774532205
  },
  {
    "productNameClean": "Esmerilhadeira e Lixadeira Angular 900w 115mm 4.1/2 11000rpm 60HZ",
    "imageUrl": "https://cf.shopee.com.br/file/br-11134207-81z1k-mgjkzgb38w7917",
    "ratingStar": "4.8",
    "priceDiscountRate": 74,
    "price": "127.9",
    "sales": 608,
    "offerLink": "https://s.shopee.com.br/6pwHTFUNPC",
    "nicho": "Ferramentas",
    "timestamp": 1774532565
  },
  {
    "productNameClean": "Cooktop de Indução Britânia Portátil Painel Touch BCTE10A",
    "imageUrl": "https://cf.shopee.com.br/file/sg-11134201-82608-mlyzbtxxuayr4a",
    "ratingStar": "4.9",
    "priceDiscountRate": 29,
    "price": "219.9",
    "sales": 175,
    "offerLink": "https://s.shopee.com.br/9fGSrhJHiY",
    "nicho": "Cozinha",
    "timestamp": 1774533649
  },
  {
    "productNameClean": "Extratora Higienizadora Portátil Vonder ELV400 400W - Limpa Estofados, Sofás...",
    "imageUrl": "https://cf.shopee.com.br/file/br-11134207-7r98o-mdn9hljmkb7d68",
    "ratingStar": "4.9",
    "priceDiscountRate": 40,
    "price": "419.9",
    "sales": 339,
    "offerLink": "https://s.shopee.com.br/6L00unnX8Y",
    "nicho": "Ferramentas",
    "timestamp": 1774534725
  },
  {
    "productNameClean": "Lava Jato de Alta Pressão Pistola Portátil Lavadora Profissional Sem...",
    "imageUrl": "https://cf.shopee.com.br/file/br-11134207-81z1k-mi5ksudk34zq4c",
    "ratingStar": "4.7",
    "priceDiscountRate": 60,
    "price": "79.97",
    "sales": 668,
    "offerLink": "https://s.shopee.com.br/AACjUG2AGa",
    "nicho": "Ferramentas",
    "timestamp": 1774535085
  },
  {
    "productNameClean": "Kit 1/Kit 2 Pilhas Recarregáveis 9V 650mAh IIgenai - USB-C...",
    "imageUrl": "https://cf.shopee.com.br/file/br-11134207-81z1k-mghbjco3turr80",
    "ratingStar": "4.9",
    "priceDiscountRate": 49,
    "price": "35.99",
    "sales": 447,
    "offerLink": "https://s.shopee.com.br/9pZt8WxXCm",
    "nicho": "Cozinha",
    "timestamp": 1774537606
  },
  {
    "productNameClean": "Kit 5 Tapete Redondo Silicone airfryer Universal Fritadeira",
    "imageUrl": "https://cf.shopee.com.br/file/sg-11134201-7qvcx-lft0enq72tk586",
    "ratingStar": "4.7",
    "priceDiscountRate": 25,
    "price": "29.99",
    "sales": 422,
    "offerLink": "https://s.shopee.com.br/70Fhljfo6N",
    "nicho": "Cozinha",
    "timestamp": 1774537965
  },
  {
    "productNameClean": "Kit 2 Balanças Digital Cozinha e Bioimpedância Para Dieta...",
    "imageUrl": "https://cf.shopee.com.br/file/sg-11134201-822xv-mi3eod0m641vb1",
    "ratingStar": "4.9",
    "priceDiscountRate": 42,
    "price": "45.99",
    "sales": 1669,
    "offerLink": "https://s.shopee.com.br/1VulE2YdxM",
    "nicho": "Cozinha",
    "timestamp": 1774538325
  },
  {
    "productNameClean": "Panela De Pressao Polida Fortlar - LAM - Escolha...",
    "imageUrl": "https://cf.shopee.com.br/file/br-11134207-7r98o-m80w2hghzuupf3",
    "ratingStar": "4.9",
    "priceDiscountRate": 27,
    "price": "50.9",
    "sales": 570,
    "offerLink": "https://s.shopee.com.br/BPNe0BtQA",
    "nicho": "Cozinha",
    "timestamp": 1774538685
  },
  {
    "productNameClean": "Kit 6 Peças Conjunto de Faca Carne Cutelo Legumes Aço...",
    "imageUrl": "https://cf.shopee.com.br/file/sg-11134201-7rdw7-mci85wat780k96",
    "ratingStar": "4.7",
    "priceDiscountRate": 40,
    "price": "23.99",
    "sales": 1039,
    "offerLink": "https://s.shopee.com.br/1BHuqFfmJl",
    "nicho": "Cozinha",
    "timestamp": 1774539045
  },
  {
    "productNameClean": "Prendedor Magnético Clipe Lacre Kit 12 Veda Fecha Alimentos Cozinha...",
    "imageUrl": "https://cf.shopee.com.br/file/br-11134207-7r98o-lq3s6x759li788",
    "ratingStar": "4.9",
    "priceDiscountRate": 57,
    "price": "21.49",
    "sales": 334,
    "offerLink": "https://s.shopee.com.br/4LEwcU1YKh",
    "nicho": "Cozinha",
    "timestamp": 1774539405
  },
  {
    "productNameClean": "Liquidificador Mondial L‑99 Turbo 550 W 3 Velocidades",
    "imageUrl": "https://cf.shopee.com.br/file/br-11134207-7r98o-mc83lzgst4gw71",
    "ratingStar": "4.9",
    "priceDiscountRate": 30,
    "price": "119.99",
    "sales": 9033,
    "offerLink": "https://s.shopee.com.br/9ztJNJE9a6",
    "nicho": "Cozinha",
    "timestamp": 1774539765
  },
  {
    "productNameClean": "Picador De Alimentos 2L 3L Moedor Elétrico Triturador Potente Carne...",
    "imageUrl": "https://cf.shopee.com.br/file/br-11134207-81z1k-me4e3redn30g5d",
    "ratingStar": "4.8",
    "priceDiscountRate": 77,
    "price": "68.99",
    "sales": 1339,
    "offerLink": "https://s.shopee.com.br/3VfpdmAahw",
    "nicho": "Cozinha",
    "timestamp": 1774540125
  },
  {
    "productNameClean": "KIT Conjunto 10 Marmita Potes 800ml com Travas Laterais BPA...",
    "imageUrl": "https://cf.shopee.com.br/file/sg-11134201-7rffe-m9txab5pqj9y5e",
    "ratingStar": "4.3",
    "priceDiscountRate": 40,
    "price": "36.04",
    "sales": 2297,
    "offerLink": "https://s.shopee.com.br/LinsMutAU",
    "nicho": "Cozinha",
    "timestamp": 1774540485
  },
  {
    "productNameClean": "Suporte Alumínio De Base Com Rodinha Para Geladeira Fogão Máquina...",
    "imageUrl": "https://cf.shopee.com.br/file/sg-11134201-8260p-mkjto48c4bnsb0",
    "ratingStar": "4.9",
    "priceDiscountRate": 40,
    "price": "28.9",
    "sales": 399,
    "offerLink": "https://s.shopee.com.br/2g6if4JUXI",
    "nicho": "Cozinha",
    "timestamp": 1774540845
  },
  {
    "productNameClean": "Kit Sifão Universal Adaptador Maquina Lavar Louça Conexão Mangueira Válvula...",
    "imageUrl": "https://cf.shopee.com.br/file/br-11134207-81z1k-meeknko5zta97f",
    "ratingStar": "4.9",
    "priceDiscountRate": 84,
    "price": "28.9",
    "sales": 235,
    "offerLink": "https://s.shopee.com.br/1VulJObKwr",
    "nicho": "Cozinha",
    "timestamp": 1774543005
  },
  {
    "productNameClean": "Kit 19 Peças Jogo de Utensílios Para Cozinha em Silicone...",
    "imageUrl": "https://cf.shopee.com.br/file/br-11134207-7r98o-m2crqyduh5dd37",
    "ratingStar": "4.6",
    "priceDiscountRate": 72,
    "price": "56.92",
    "sales": 1223,
    "offerLink": "https://s.shopee.com.br/1VulJoDDqe",
    "nicho": "Cozinha",
    "timestamp": 1774543365
  },
  {
    "productNameClean": "Frigideiras Ceramica Antiaderente Fogão Cooktop Indução Gás Elétrico Premium Profissional",
    "imageUrl": "https://cf.shopee.com.br/file/br-11134207-81zu6-mkn1dswifq4g5e",
    "ratingStar": "4.9",
    "priceDiscountRate": 34,
    "price": "65.97",
    "sales": 962,
    "offerLink": "https://s.shopee.com.br/AACje9E7yA",
    "nicho": "Cozinha",
    "timestamp": 1774543725
  },
  {
    "productNameClean": "Máquina de Donuts Rosquinhas Confeitaria Culinária 110v",
    "imageUrl": "https://cf.shopee.com.br/file/br-11134207-81ztc-mjhvlpktcutf65",
    "ratingStar": "4.8",
    "priceDiscountRate": 57,
    "price": "54.99",
    "sales": 112,
    "offerLink": "https://s.shopee.com.br/9AKCSipphn",
    "nicho": "Cozinha",
    "timestamp": 1774544085
  },
  {
    "productNameClean": "Cozedor de Ovos Elétrico Portátil Cozinha à Vapor 110v...",
    "imageUrl": "https://cf.shopee.com.br/file/br-11134207-81z1k-mepurq90i32acf",
    "ratingStar": "4.9",
    "priceDiscountRate": 45,
    "price": "49.44",
    "sales": 513,
    "offerLink": "https://s.shopee.com.br/4qBDJAZpU7",
    "nicho": "Cozinha",
    "timestamp": 1774544445
  },
  {
    "productNameClean": "Ventilador de Teto LED 60W 80W Lâmpada E27 Controle Remoto...",
    "imageUrl": "https://cf.shopee.com.br/file/cn-11134207-820l4-mkixsca7ixaacf",
    "ratingStar": "4.8",
    "priceDiscountRate": 59,
    "price": "46.9",
    "sales": 2540,
    "offerLink": "https://s.shopee.com.br/W2E9DH8XG",
    "nicho": "Casa",
    "timestamp": 1774544450
  },
  {
    "productNameClean": "Kit Balança Digital de Precisão e Bioimpedância para nutrição...",
    "imageUrl": "https://cf.shopee.com.br/file/br-11134207-7r98o-m68erxw0gfwl5d",
    "ratingStar": "4.9",
    "priceDiscountRate": 48,
    "price": "49.9",
    "sales": 360,
    "offerLink": "https://s.shopee.com.br/5Ao3ibj1zd",
    "nicho": "Cozinha",
    "timestamp": 1774545165
  },
  {
    "productNameClean": "Suporte De Base Com Rodinha Para Geladeira Fogão Máquina Lavar...",
    "imageUrl": "https://cf.shopee.com.br/file/sg-11134201-7rffw-m4axof9tz8w85c",
    "ratingStar": "4.9",
    "priceDiscountRate": 57,
    "price": "29.99",
    "sales": 3870,
    "offerLink": "https://s.shopee.com.br/9Kdcgg0nDl",
    "nicho": "Cozinha",
    "timestamp": 1774545525
  },
  {
    "productNameClean": "Air Fryer Oven Britânia 12L 4 em 1 1800W BFR2100",
    "imageUrl": "https://cf.shopee.com.br/file/sg-11134201-82615-mlyyowciz5dsfd",
    "ratingStar": "4.9",
    "priceDiscountRate": 33,
    "price": "499.9",
    "sales": 748,
    "offerLink": "https://s.shopee.com.br/5VQu8SLBNy",
    "nicho": "Cozinha",
    "timestamp": 1774546245
  },
  {
    "productNameClean": "Liquidificador Portátil Recarregável 8 Lâminas, Automatico Suco Smoothies Vitaminas Leite",
    "imageUrl": "https://cf.shopee.com.br/file/sg-11134201-825zx-mjaqmjmhj01v63",
    "ratingStar": "4.7",
    "priceDiscountRate": 56,
    "price": "43.99",
    "sales": 396,
    "offerLink": "https://s.shopee.com.br/3LMPZIZdmH",
    "nicho": "Cozinha",
    "timestamp": 1774546965
  },
  {
    "productNameClean": "Rolo Gofrado Embalagem a Vácuo Para Seladora Doméstica Freezer Alimentos...",
    "imageUrl": "https://cf.shopee.com.br/file/br-11134207-7r98o-m8koa2ui40z5f3",
    "ratingStar": "4.9",
    "priceDiscountRate": 61,
    "price": "20.99",
    "sales": 2501,
    "offerLink": "https://s.shopee.com.br/50UdYm0mXI",
    "nicho": "Cozinha",
    "timestamp": 1774547325
  },
  {
    "productNameClean": "Fatiador de cozinha multifuncional profissional em aço inoxidável 16...",
    "imageUrl": "https://cf.shopee.com.br/file/cn-11134207-7ras8-maozriowdjfw01",
    "ratingStar": "4.8",
    "priceDiscountRate": 40,
    "price": "34.8",
    "sales": 3340,
    "offerLink": "https://s.shopee.com.br/1gEBb3lRFZ",
    "nicho": "Cozinha",
    "timestamp": 1774547685
  },
  {
    "productNameClean": "Aspirador de Pó Para Casa Robô Inteligente Com Sensores Anti...",
    "imageUrl": "https://cf.shopee.com.br/file/sg-11134201-7rdwh-lxr9gcah5u3jd7",
    "ratingStar": "4.9",
    "priceDiscountRate": 50,
    "price": "499.99",
    "sales": 3415,
    "offerLink": "https://s.shopee.com.br/8fNvwKscUz",
    "nicho": "Casa",
    "timestamp": 1774548045
  },
  {
    "productNameClean": "Máquina de Lavar Twin Tub Praxis 10kg 2 em 1...",
    "imageUrl": "https://cf.shopee.com.br/file/sg-11134201-824hf-mfobvevqv4soc6",
    "ratingStar": "4.9",
    "priceDiscountRate": 25,
    "price": "1031.9",
    "sales": 361,
    "offerLink": "https://s.shopee.com.br/8Kl5XjFt7x",
    "nicho": "Casa",
    "timestamp": 1774548049
  },
  {
    "productNameClean": "Kit 2 Mesas de Cabeceira Retro para Quarto Casal ou...",
    "imageUrl": "https://cf.shopee.com.br/file/sg-11134201-7rd6k-lv8yit7piy8947",
    "ratingStar": "4.8",
    "priceDiscountRate": 45,
    "price": "54.9",
    "sales": 2550,
    "offerLink": "https://s.shopee.com.br/1BHv0xtTzS",
    "nicho": "Casa",
    "timestamp": 1774548405
  },
  {
    "productNameClean": "kit8-24protetor de silicone para pés de cadeiras e mesas ...",
    "imageUrl": "https://cf.shopee.com.br/file/sg-11134201-821g8-mgjizhaa3jm18e",
    "ratingStar": "4.9",
    "priceDiscountRate": 27,
    "price": "22.99",
    "sales": 990,
    "offerLink": "https://s.shopee.com.br/9KdckNvsYN",
    "nicho": "Casa",
    "timestamp": 1774548765
  },
  {
    "productNameClean": "Conjunto Corrente Para Vaso De Flores Ao Ar Livre...",
    "imageUrl": "https://cf.shopee.com.br/file/sg-11134201-7rdxl-m19yqwdmabdkf0",
    "ratingStar": "4.9",
    "priceDiscountRate": 59,
    "price": "29.99",
    "sales": 703,
    "offerLink": "https://s.shopee.com.br/8fNvxZWNsI",
    "nicho": "Casa",
    "timestamp": 1774549125
  },
  {
    "productNameClean": "Cortina Blackout PVC Corta 100% a Luz 2,80 m x...",
    "imageUrl": "https://cf.shopee.com.br/file/br-11134207-7r98o-mb474mel7ounad",
    "ratingStar": "4.8",
    "priceDiscountRate": 20,
    "price": "64.34",
    "sales": 3531,
    "offerLink": "https://s.shopee.com.br/3fzG0nNf46",
    "nicho": "Casa",
    "timestamp": 1774549485
  },
  {
    "productNameClean": "Espelho Redondo Decorativo Adnet Alça 60cm e 50cm Sala Quarto...",
    "imageUrl": "https://cf.shopee.com.br/file/br-11134207-7r98o-mcrsq74qbhfl83",
    "ratingStar": "4.8",
    "priceDiscountRate": 29,
    "price": "37",
    "sales": 2342,
    "offerLink": "https://s.shopee.com.br/gLeRh6dWI",
    "nicho": "Casa",
    "timestamp": 1774549845
  },
  {
    "productNameClean": "Kit 2 Travesseiros Toque De Pluma 50x70 Extra Macio 100%",
    "imageUrl": "https://cf.shopee.com.br/file/br-11134207-81ztc-mj42bfo7yhhe79",
    "ratingStar": "4.7",
    "priceDiscountRate": 48,
    "price": "25.9",
    "sales": 5675,
    "offerLink": "https://s.shopee.com.br/7fVOmyE5p0",
    "nicho": "Casa",
    "timestamp": 1774550205
  },
  {
    "productNameClean": "Refil Via Aroma 1l Agua Perfumada Aromatizador Tecido Roupas Via...",
    "imageUrl": "https://cf.shopee.com.br/file/sg-11134201-7raux-ma349igfb7vm3f",
    "ratingStar": "4.9",
    "priceDiscountRate": 40,
    "price": "55.8",
    "sales": 273,
    "offerLink": "https://s.shopee.com.br/3B2zR73GAn",
    "nicho": "Casa",
    "timestamp": 1774550565
  },
  {
    "productNameClean": "Roupeiro Guarda Roupa Portatil Cabideiro Arara Para Roupa Sapateira Organizador...",
    "imageUrl": "https://cf.shopee.com.br/file/sg-11134201-7rbkt-m642rqkvabq625",
    "ratingStar": "4.8",
    "priceDiscountRate": 54,
    "price": "94.49",
    "sales": 1617,
    "offerLink": "https://s.shopee.com.br/BPNs0mEfg",
    "nicho": "Casa",
    "timestamp": 1774550925
  },
  {
    "productNameClean": "Secador Roupas Portátil Eletrico Secador Suspenso Cortina JH",
    "imageUrl": "https://cf.shopee.com.br/file/sg-11134201-824id-merhk8li10qsfd",
    "ratingStar": "4.8",
    "priceDiscountRate": 35,
    "price": "129.99",
    "sales": 83,
    "offerLink": "https://s.shopee.com.br/7fVOoclp93",
    "nicho": "Casa",
    "timestamp": 1774551649
  },
  {
    "productNameClean": "Ferro Passar Roupa a Vapor e Seco Bivolt 127V/220V",
    "imageUrl": "https://cf.shopee.com.br/file/br-11134207-81zuo-mkjx6u3wga9sf7",
    "ratingStar": "4.8",
    "priceDiscountRate": 71,
    "price": "58.98",
    "sales": 221,
    "offerLink": "https://s.shopee.com.br/8fNw0rtmJZ",
    "nicho": "Casa",
    "timestamp": 1774552006
  },
  {
    "productNameClean": "Kit 2 / 1 / 4 Travesseiro Pluma de Ganso...",
    "imageUrl": "https://cf.shopee.com.br/file/br-11134207-81z1k-mhs10tgrfev7e6",
    "ratingStar": "4.7",
    "priceDiscountRate": 81,
    "price": "21.1",
    "sales": 7939,
    "offerLink": "https://s.shopee.com.br/5Ao3qqenLx",
    "nicho": "Casa",
    "timestamp": 1774552365
  },
  {
    "productNameClean": "Kit Umidificador De Ar + 3 Essências 10ml | Difusor...",
    "imageUrl": "https://cf.shopee.com.br/file/br-11134207-81z1k-mflnxsd5vnyf22",
    "ratingStar": "4.8",
    "priceDiscountRate": 45,
    "price": "25.5",
    "sales": 1503,
    "offerLink": "https://s.shopee.com.br/2BASHkO2ri",
    "nicho": "Casa",
    "timestamp": 1774552725
  },
  {
    "productNameClean": "KIT 4 Caixa com Tampa de Armazenamento para Roupas, Brinquedos...",
    "imageUrl": "https://cf.shopee.com.br/file/sg-11134201-8262b-mlm7kqr81iioca",
    "ratingStar": "4.9",
    "priceDiscountRate": 27,
    "price": "79.99",
    "sales": 2616,
    "offerLink": "https://s.shopee.com.br/Lio6n3Krj",
    "nicho": "Casa",
    "timestamp": 1774553085
  },
  {
    "productNameClean": "Kit com 2 Mesa de Cabeceira Nicho Organizador, pés retrô...",
    "imageUrl": "https://cf.shopee.com.br/file/br-11134207-81ztc-mjulrjf28q2q0a",
    "ratingStar": "4.8",
    "priceDiscountRate": 41,
    "price": "124.8",
    "sales": 2690,
    "offerLink": "https://s.shopee.com.br/8V4VqD68zz",
    "nicho": "Casa",
    "timestamp": 1774553445
  },
  {
    "productNameClean": "Kit 3 Toalhas de Piso Luxo antiderrapante Tapete p/ Banheiro",
    "imageUrl": "https://cf.shopee.com.br/file/sg-11134201-8225i-mhpcyu1q53pgd2",
    "ratingStar": "4.9",
    "priceDiscountRate": 45,
    "price": "35.9",
    "sales": 627,
    "offerLink": "https://s.shopee.com.br/9fGTElZG29",
    "nicho": "Casa",
    "timestamp": 1774553805
  },
  {
    "productNameClean": "Fechadura de Porta Residencial Sala Cozinha Quarto e Banheiro Soprano...",
    "imageUrl": "https://cf.shopee.com.br/file/br-11134207-81z1k-me4ehqb1pxq995",
    "ratingStar": "4.9",
    "priceDiscountRate": 10,
    "price": "36",
    "sales": 751,
    "offerLink": "https://s.shopee.com.br/2LTsVhZ4dz",
    "nicho": "Casa",
    "timestamp": 1774554165
  },
  {
    "productNameClean": "Espelho Redondo Decorativo Adnet Couro Costurado 60cm Sala Quarto Banheiro...",
    "imageUrl": "https://cf.shopee.com.br/file/br-11134207-820lg-mlpbs76nr2f9d6",
    "ratingStar": "4.9",
    "priceDiscountRate": 69,
    "price": "24.9",
    "sales": 6701,
    "offerLink": "https://s.shopee.com.br/7fVOrumsHn",
    "nicho": "Casa",
    "timestamp": 1774554525
  },
  {
    "productNameClean": "Rede de Descanso Jeans Life Basic até 2 Pessoas 3.90m...",
    "imageUrl": "https://cf.shopee.com.br/file/br-11134207-7r98o-m759a0kn35m8c9",
    "ratingStar": "4.9",
    "priceDiscountRate": 66,
    "price": "49.9",
    "sales": 875,
    "offerLink": "https://s.shopee.com.br/8V4VtVTC80",
    "nicho": "Casa",
    "timestamp": 1774556325
  },
  {
    "productNameClean": "Kit 3 Organizadores De Gaveta De Sutiã Dobrável Caixa...",
    "imageUrl": "https://cf.shopee.com.br/file/sg-11134201-7rd5r-m73vrgl7203w6c",
    "ratingStar": "4.8",
    "priceDiscountRate": 61,
    "price": "23.6",
    "sales": 1253,
    "offerLink": "https://s.shopee.com.br/15xmIXS5a",
    "nicho": "Casa",
    "timestamp": 1774556685
  },
  {
    "productNameClean": "ÁGUA PERFUMADA 500ML VIA AROMA SPRAY PARA TECIDO CHEIRINHO...",
    "imageUrl": "https://cf.shopee.com.br/file/br-11134207-81z1k-meu0hjpeyry9d4",
    "ratingStar": "4.9",
    "priceDiscountRate": 40,
    "price": "29.99",
    "sales": 572,
    "offerLink": "https://s.shopee.com.br/7pop76bK8N",
    "nicho": "Casa",
    "timestamp": 1774557045
  },
  {
    "productNameClean": "Cortina Roma 2,40 x 1,70 Para Janela, Sala, Quarto, Decoração...",
    "imageUrl": "https://cf.shopee.com.br/file/73744becb70af619af84ae1eff7b7e80",
    "ratingStar": "4.6",
    "priceDiscountRate": 40,
    "price": "29.8",
    "sales": 5951,
    "offerLink": "https://s.shopee.com.br/3qIgMZwLfa",
    "nicho": "Casa",
    "timestamp": 1774557766
  },
  {
    "productNameClean": "Kit 5 Toalhas de Piso Atoalhado Com Ou Sem Estampa...",
    "imageUrl": "https://cf.shopee.com.br/file/br-11134207-7r98o-lrp17sdym78ke0",
    "ratingStar": "4.6",
    "priceDiscountRate": 53,
    "price": "36.9",
    "sales": 792,
    "offerLink": "https://s.shopee.com.br/4qBDYpQmdA",
    "nicho": "Casa",
    "timestamp": 1774558125
  },
  {
    "productNameClean": "Caneta Depilador Sobrancelha Elétrico Removedor Tira Pelos USB Recarregável",
    "imageUrl": "https://cf.shopee.com.br/file/br-11134207-81ztc-mjy53m01v9q9a6",
    "ratingStar": "4.8",
    "priceDiscountRate": 67,
    "price": "19.99",
    "sales": 39,
    "offerLink": "https://s.shopee.com.br/3VfpyS7Qdp",
    "nicho": "Beleza_e_Estilo",
    "timestamp": 1774558189
  },
  {
    "productNameClean": "Esfoliante Corpo e Rosto Labotrat Dia a Dia - 300g",
    "imageUrl": "https://cf.shopee.com.br/file/sg-11134201-7rdyo-m0dlsnnjp4jy8b",
    "ratingStar": "4.9",
    "priceDiscountRate": 50,
    "price": "29.9",
    "sales": 341,
    "offerLink": "https://s.shopee.com.br/8ARfXmJTkX",
    "nicho": "Beleza_e_Estilo",
    "timestamp": 1774558845
  },
  {
    "productNameClean": "Bicicleta Ergométrica Spinning Magnética Gallant Elite X Roda de Inércia...",
    "imageUrl": "https://cf.shopee.com.br/file/sg-11134201-7rbni-m5keaeaqgpu213",
    "ratingStar": "4.9",
    "priceDiscountRate": 16,
    "price": "2109",
    "sales": 18,
    "offerLink": "https://s.shopee.com.br/4VYNB2tR9x",
    "nicho": "Beleza_e_Estilo",
    "timestamp": 1774558850
  },
  {
    "productNameClean": "Maquina De Cortar Cabelo Profissional Smart LCD Barbeador Eletrico Transparente...",
    "imageUrl": "https://cf.shopee.com.br/file/br-11134207-81ztc-mji5lj4eeccj78",
    "ratingStar": "4.7",
    "priceDiscountRate": 75,
    "price": "24.69",
    "sales": 2137,
    "offerLink": "https://s.shopee.com.br/7AZ8MLvFhd",
    "nicho": "Beleza_e_Estilo",
    "timestamp": 1774559205
  },
  {
    "productNameClean": "Máquina Shaver Profissional Sem Fio USB-C Acabamento Rente B-MAX",
    "imageUrl": "https://cf.shopee.com.br/file/br-11134207-81zu8-mksegtnh5b0h9f",
    "ratingStar": "4.7",
    "priceDiscountRate": 42,
    "price": "57.9",
    "sales": 291,
    "offerLink": "https://s.shopee.com.br/808FMIQBVY",
    "nicho": "Beleza_e_Estilo",
    "timestamp": 1774559565
  },
  {
    "productNameClean": "Camiseta Masculina Canelada estilo Americana RAPPER Blusa Camisa Slim Americana...",
    "imageUrl": "https://cf.shopee.com.br/file/br-11134207-7r98o-m55v6dj2d11h01",
    "ratingStar": "4.9",
    "priceDiscountRate": 40,
    "price": "29.99",
    "sales": 1376,
    "offerLink": "https://s.shopee.com.br/30jZPWGuZU",
    "nicho": "Beleza_e_Estilo",
    "timestamp": 1774559925
  },
  {
    "productNameClean": "Kit Suplemento Prebiótica 4Mag Magnésio Fórmula NAC Rituária",
    "imageUrl": "https://cf.shopee.com.br/file/br-11134207-81z1k-mggwaa1rk1kwd3",
    "ratingStar": "4.9",
    "priceDiscountRate": 30,
    "price": "179.83",
    "sales": 611,
    "offerLink": "https://s.shopee.com.br/W2ERKyX9K",
    "nicho": "Beleza_e_Estilo",
    "timestamp": 1774560285
  },
  {
    "productNameClean": "Secador de Cabelo 110v Profissional 3200W - Voltagem 110v",
    "imageUrl": "https://cf.shopee.com.br/file/cb910bb6f3dac3704fb1ac142dac4b66",
    "ratingStar": "4.4",
    "priceDiscountRate": 66,
    "price": "58.98",
    "sales": 776,
    "offerLink": "https://s.shopee.com.br/W2ERkWQqD",
    "nicho": "Beleza_e_Estilo",
    "timestamp": 1774560645
  },
  {
    "productNameClean": "Kit 10 Cuecas Boxer Masculina Adulto Microfibra",
    "imageUrl": "https://cf.shopee.com.br/file/br-11134207-81z1k-mhhphornkdfn2b",
    "ratingStar": "4.4",
    "priceDiscountRate": 44,
    "price": "27.94",
    "sales": 1606,
    "offerLink": "https://s.shopee.com.br/AACjykZSsD",
    "nicho": "Beleza_e_Estilo",
    "timestamp": 1774561725
  },
  {
    "productNameClean": "Máquina De Cortar Cabelo Para Barba Masculina Designer Elétrico Profissional...",
    "imageUrl": "https://cf.shopee.com.br/file/br-11134207-820ma-mm8ne7wxt91c83",
    "ratingStar": "4.8",
    "priceDiscountRate": 47,
    "price": "20.98",
    "sales": 3065,
    "offerLink": "https://s.shopee.com.br/2qQ9FgZ8vk",
    "nicho": "Beleza_e_Estilo",
    "timestamp": 1774562085
  },
  {
    "productNameClean": "Kit 12 Esfoliante Hidratante Corporal 180g Soul Cosméticos",
    "imageUrl": "https://cf.shopee.com.br/file/br-11134207-7r98o-m8nr01htrv695a",
    "ratingStar": "4.9",
    "priceDiscountRate": 31,
    "price": "89.9",
    "sales": 256,
    "offerLink": "https://s.shopee.com.br/7fVP0yodrE",
    "nicho": "Beleza_e_Estilo",
    "timestamp": 1774562445
  },
  {
    "productNameClean": "Punho Magnético Para Câmera E Luz Selfie , Kit Criador...",
    "imageUrl": "https://cf.shopee.com.br/file/cn-11134207-820l4-mj3xwal3fjluc2",
    "ratingStar": "4.8",
    "priceDiscountRate": 28,
    "price": "75.99",
    "sales": 36,
    "offerLink": "https://s.shopee.com.br/70FiDlCu54",
    "nicho": "Tech_e_Gadgets",
    "timestamp": 1774562449
  },
  {
    "productNameClean": "Kit Masculino 3 Body Splash Kayak + Essenciale + Malbec...",
    "imageUrl": "https://cf.shopee.com.br/file/br-11134207-7r98o-md3a7mzb26gi46",
    "ratingStar": "4.6",
    "priceDiscountRate": 51,
    "price": "44",
    "sales": 2352,
    "offerLink": "https://s.shopee.com.br/30jZSoe6GQ",
    "nicho": "Beleza_e_Estilo",
    "timestamp": 1774562805
  },
  {
    "productNameClean": "Kit 2 Regatas Longline Masculina Oversized - Combo Poliéster...",
    "imageUrl": "https://cf.shopee.com.br/file/br-11134207-81z1k-meoq0gfhovsx73",
    "ratingStar": "4.7",
    "priceDiscountRate": 51,
    "price": "38.9",
    "sales": 584,
    "offerLink": "https://s.shopee.com.br/7popFl5Bwy",
    "nicho": "Beleza_e_Estilo",
    "timestamp": 1774564605
  },
  {
    "productNameClean": "ROMANTIC CROWN Copo Térmico Inox Portátil 1200ml/600ml/1.2L Garrafa Térmica Inoxidável...",
    "imageUrl": "https://cf.shopee.com.br/file/br-11134207-81ztc-mj2ddyi3zfgi6a",
    "ratingStar": "4.9",
    "priceDiscountRate": 50,
    "price": "39.98",
    "sales": 10477,
    "offerLink": "https://s.shopee.com.br/6VJRfiiNAJ",
    "nicho": "Beleza_e_Estilo",
    "timestamp": 1774564965
  },
  {
    "productNameClean": "Novo Creme Dental Branqueador De Dentes 5D Higiene Oral Limpeza...",
    "imageUrl": "https://cf.shopee.com.br/file/sg-11134201-8260i-mj8f0t37faww85",
    "ratingStar": "4.5",
    "priceDiscountRate": 24,
    "price": "27.49",
    "sales": 121,
    "offerLink": "https://s.shopee.com.br/6L01TpCdw5",
    "nicho": "Beleza_e_Estilo",
    "timestamp": 1774565325
  },
  {
    "productNameClean": "LANÇAMENTO • iPhone 17 Pro / 17 Pro Max 256GB...",
    "imageUrl": "https://cf.shopee.com.br/file/br-11134207-81z1k-mhcaeeg33imda2",
    "ratingStar": "4.8",
    "priceDiscountRate": 41,
    "price": "8899",
    "sales": 252,
    "offerLink": "https://s.shopee.com.br/BPO9Jju4I",
    "nicho": "Tech_e_Gadgets",
    "timestamp": 1774566045
  },
  {
    "productNameClean": "Mesa Controle Placa De Som Com Microfone E Brago Articulado",
    "imageUrl": "https://cf.shopee.com.br/file/br-11134207-81z1k-mhsnry4iimfa3a",
    "ratingStar": "4.9",
    "priceDiscountRate": 69,
    "price": "156.97",
    "sales": 83,
    "offerLink": "https://s.shopee.com.br/9ztJrOUXMv",
    "nicho": "Tech_e_Gadgets",
    "timestamp": 1774566050
  },
  {
    "productNameClean": "Pasta Térmica Ts-Cold com Limpador Multiuso Alto Desempenho Kit...",
    "imageUrl": "https://cf.shopee.com.br/file/br-11134207-81z1k-mg2eb5cinsw72d",
    "ratingStar": "4.9",
    "priceDiscountRate": 31,
    "price": "51.48",
    "sales": 219,
    "offerLink": "https://s.shopee.com.br/qf4wxFKgN",
    "nicho": "Tech_e_Gadgets",
    "timestamp": 1774566405
  },
  {
    "productNameClean": "Kit Mobilador Gamer Para Celular Com Teclado Mouse Tripé ...",
    "imageUrl": "https://cf.shopee.com.br/file/br-11134207-7qukw-lk752o9bliqu4d",
    "ratingStar": "4.7",
    "priceDiscountRate": 33,
    "price": "29",
    "sales": 375,
    "offerLink": "https://s.shopee.com.br/8ARfgqLWIf",
    "nicho": "Tech_e_Gadgets",
    "timestamp": 1774566765
  },
  {
    "productNameClean": "Smart Watch Relogio WL X-mini inteligente 38mm series 10 2025...",
    "imageUrl": "https://cf.shopee.com.br/file/sg-11134201-824ga-mely0px5h2ivc5",
    "ratingStar": "4.7",
    "priceDiscountRate": 71,
    "price": "49.98",
    "sales": 1113,
    "offerLink": "https://s.shopee.com.br/8V4W5rrsJ7",
    "nicho": "Tech_e_Gadgets",
    "timestamp": 1774567125
  },
  {
    "productNameClean": "Hd Full 1080P Câmera Webcam Para Computador Visão 360º",
    "imageUrl": "https://cf.shopee.com.br/file/br-11134201-23010-esnhmpcw7amv17",
    "ratingStar": "4.4",
    "priceDiscountRate": 34,
    "price": "29.88",
    "sales": 361,
    "offerLink": "https://s.shopee.com.br/9ztJt2G4lQ",
    "nicho": "Tech_e_Gadgets",
    "timestamp": 1774567485
  },
  {
    "productNameClean": "Caixa De Som C/ Microfones Alto-falante Bluetooth Karaoke com Microfone...",
    "imageUrl": "https://cf.shopee.com.br/file/br-11134207-820m7-mm89a2l7g7bba7",
    "ratingStar": "4.8",
    "priceDiscountRate": 74,
    "price": "29.98",
    "sales": 3050,
    "offerLink": "https://s.shopee.com.br/2VnIytycYn",
    "nicho": "Tech_e_Gadgets",
    "timestamp": 1774568925
  },
  {
    "productNameClean": "Filamento PETG / PLA MasterPrint Premium 1Kg Impressora 3D Várias...",
    "imageUrl": "https://cf.shopee.com.br/file/sg-11134201-821dy-mh953q41sqvg55",
    "ratingStar": "4.8",
    "priceDiscountRate": 50,
    "price": "63.9",
    "sales": 1935,
    "offerLink": "https://s.shopee.com.br/3B2zmXPAa5",
    "nicho": "Tech_e_Gadgets",
    "timestamp": 1774569285
  },
  {
    "productNameClean": "Massageador elétrico Pistola de massagem elétrica Massageador portátil para tecidos...",
    "imageUrl": "https://cf.shopee.com.br/file/br-11134207-820mg-mma2cbgeh8nbcc",
    "ratingStar": "4.9",
    "priceDiscountRate": 74,
    "price": "38.89",
    "sales": 5785,
    "offerLink": "https://s.shopee.com.br/4VYNNOwnvK",
    "nicho": "Tech_e_Gadgets",
    "timestamp": 1774569645
  },
  {
    "productNameClean": "Mini Projetor De Luz Noturna Estrela De Astronauta Decoração...",
    "imageUrl": "https://cf.shopee.com.br/file/sg-11134201-7rdwr-m0ulj3witu9140",
    "ratingStar": "4.9",
    "priceDiscountRate": 65,
    "price": "39.99",
    "sales": 184,
    "offerLink": "https://s.shopee.com.br/9fGTWtyn4O",
    "nicho": "Tech_e_Gadgets",
    "timestamp": 1774569649
  },
  {
    "productNameClean": "Mini Câmera de Segurança WiFi 360° Visão Noturna Áudio Bidirecional...",
    "imageUrl": "https://cf.shopee.com.br/file/sg-11134201-82629-mlbse7zffsao1e",
    "ratingStar": "4.8",
    "priceDiscountRate": 44,
    "price": "54.9",
    "sales": 105,
    "offerLink": "https://s.shopee.com.br/5VQuZeQU18",
    "nicho": "Tech_e_Gadgets",
    "timestamp": 1774570006
  },
  {
    "productNameClean": "Projetor 4K HD 150 polegadas para celular, TV Box, Xbox...",
    "imageUrl": "https://cf.shopee.com.br/file/sg-11134201-8261g-ml83609qn21167",
    "ratingStar": "4.8",
    "priceDiscountRate": 78,
    "price": "172.99",
    "sales": 815,
    "offerLink": "https://s.shopee.com.br/3qIgb04nMo",
    "nicho": "Tech_e_Gadgets",
    "timestamp": 1774570365
  },
  {
    "productNameClean": "Kit 1 e 2 un Microfones Sem Fio Sinal Forte...",
    "imageUrl": "https://cf.shopee.com.br/file/br-11134207-7r98o-lxldvp3avlxb37",
    "ratingStar": "4.8",
    "priceDiscountRate": 55,
    "price": "49.99",
    "sales": 423,
    "offerLink": "https://s.shopee.com.br/gLepap5pN",
    "nicho": "Tech_e_Gadgets",
    "timestamp": 1774570725
  },
  {
    "productNameClean": "Kit Teclado Gamer para Celular - Compatível com Vários Modelos...",
    "imageUrl": "https://cf.shopee.com.br/file/br-11134207-7r98o-lqyyycdntgjxb2",
    "ratingStar": "4.7",
    "priceDiscountRate": 63,
    "price": "50.9",
    "sales": 479,
    "offerLink": "https://s.shopee.com.br/15y3Bx11H",
    "nicho": "Tech_e_Gadgets",
    "timestamp": 1774571445
  },
  {
    "productNameClean": "Fones de ouvido sem fio Bluetooth compactos Xiaomi Redmi Airdots...",
    "imageUrl": "https://cf.shopee.com.br/file/br-11134207-820la-mltkawis4qo439",
    "ratingStar": "4.7",
    "priceDiscountRate": 60,
    "price": "21.79",
    "sales": 2770,
    "offerLink": "https://s.shopee.com.br/AUpaYtrDSR",
    "nicho": "Tech_e_Gadgets",
    "timestamp": 1774571805
  },
  {
    "productNameClean": "Webcam Full HD 1080p com Microfone Embutido - Widescreen USB...",
    "imageUrl": "https://cf.shopee.com.br/file/br-11134207-7r98o-m0mrklj0on6l51",
    "ratingStar": "4.8",
    "priceDiscountRate": 59,
    "price": "77",
    "sales": 101,
    "offerLink": "https://s.shopee.com.br/5L7UPoimds",
    "nicho": "Tech_e_Gadgets",
    "timestamp": 1774572165
  },
  {
    "productNameClean": "Estabilizador de Celular Portátil Gimbal Rastreamento Facial IA Tripé Dobrável...",
    "imageUrl": "https://cf.shopee.com.br/file/br-11134207-7r98o-m6zxi922u3ao11",
    "ratingStar": "4.9",
    "priceDiscountRate": 18,
    "price": "329.8",
    "sales": 217,
    "offerLink": "https://s.shopee.com.br/7AZ8bb9Uq9",
    "nicho": "Tech_e_Gadgets",
    "timestamp": 1774572525
  },
  {
    "productNameClean": "INOVA power bank 20000 mah turbo Carregador Portátil Universal Original...",
    "imageUrl": "https://cf.shopee.com.br/file/br-11134207-81z1k-mf530vlsia6d2a",
    "ratingStar": "4.9",
    "priceDiscountRate": 46,
    "price": "114.98",
    "sales": 937,
    "offerLink": "https://s.shopee.com.br/LioTS7L9j",
    "nicho": "Tech_e_Gadgets",
    "timestamp": 1774572885
  },
  {
    "productNameClean": "KZ ZSN PRO X Fones De Ouvido TWS Sem Fio...",
    "imageUrl": "https://cf.shopee.com.br/file/sg-11134201-8261c-mk0omonvrta9ca",
    "ratingStar": "5",
    "priceDiscountRate": 46,
    "price": "67.82",
    "sales": 3,
    "offerLink": "https://s.shopee.com.br/9AKD05coXm",
    "nicho": "Tech_e_Gadgets",
    "timestamp": 1774573238
  },
  {
    "productNameClean": "2026 Smartwatch T10 Ultra 3 Nova Série 10 SmartWatch 2.09...",
    "imageUrl": "https://cf.shopee.com.br/file/br-11134207-7r98o-lynjf3lq609x48",
    "ratingStar": "4.7",
    "priceDiscountRate": 61,
    "price": "58.8",
    "sales": 1148,
    "offerLink": "https://s.shopee.com.br/6L01ctISyZ",
    "nicho": "Tech_e_Gadgets",
    "timestamp": 1774573245
  },
  {
    "productNameClean": "Hoverboard Infantil 6.5\" - Skate Elétrico com LED Bluetooth...",
    "imageUrl": "https://cf.shopee.com.br/file/sg-11134201-7rdyo-mc8voa3qfn5ee2",
    "ratingStar": "4.8",
    "priceDiscountRate": 30,
    "price": "559.39",
    "sales": 272,
    "offerLink": "https://s.shopee.com.br/6L01dJPUgP",
    "nicho": "Tech_e_Gadgets",
    "timestamp": 1774573614
  },
  {
    "productNameClean": "Webcam Câmera Full Hd 1080p 360 Graus Videoconferência Streamcam Web...",
    "imageUrl": "https://cf.shopee.com.br/file/sg-11134201-7ratl-mabme1oxej7i39",
    "ratingStar": "4.8",
    "priceDiscountRate": 29,
    "price": "49.99",
    "sales": 223,
    "offerLink": "https://s.shopee.com.br/AKWAPDwCHK",
    "nicho": "Tech_e_Gadgets",
    "timestamp": 1774574103
  },
  {
    "productNameClean": "Grade De Proteção Reforçada Para Camera Cftv Segurança Dome Bullet...",
    "imageUrl": "https://cf.shopee.com.br/file/br-11134207-7r98o-m64i876mdx0068",
    "ratingStar": "4.8",
    "priceDiscountRate": 17,
    "price": "30.3",
    "sales": 170,
    "offerLink": "https://s.shopee.com.br/5fkKriI1y4",
    "nicho": "Tech_e_Gadgets",
    "timestamp": 1774575034
  },
  {
    "productNameClean": "Basike Estabilizador Smart XE Gimbal para Smartphone Portátil Rastreamento Tripé...",
    "imageUrl": "https://cf.shopee.com.br/file/br-11134207-81z1k-mg7shvpxe4n841",
    "ratingStar": "4.8",
    "priceDiscountRate": 62,
    "price": "149.9",
    "sales": 111,
    "offerLink": "https://s.shopee.com.br/900mqFdJAP",
    "nicho": "Tech_e_Gadgets",
    "timestamp": 1774575394
  },
  {
    "productNameClean": "Hoverkart Para Hoverboard Carrinho Ajustável 10 A 6,5",
    "imageUrl": "https://cf.shopee.com.br/file/br-11134207-81z1k-mhzj9lb50d8ib2",
    "ratingStar": "4.9",
    "priceDiscountRate": 48,
    "price": "309",
    "sales": 107,
    "offerLink": "https://s.shopee.com.br/2LTsuPWBeP",
    "nicho": "Tech_e_Gadgets",
    "timestamp": 1774575754
  },
  {
    "productNameClean": "Power Bank 20000mAh com Visor Digital: Carregamento Ultra-Rápido e 4...",
    "imageUrl": "https://cf.shopee.com.br/file/sg-11134201-81zv1-miv9q3tt0qo13d",
    "ratingStar": "4.9",
    "priceDiscountRate": 28,
    "price": "71.9",
    "sales": 235,
    "offerLink": "https://s.shopee.com.br/1LbLjUQNFC",
    "nicho": "Tech_e_Gadgets",
    "timestamp": 1774576555
  },
  {
    "productNameClean": "Caixa De Som Com Microfone Alto-Falante Karaokê sem fio Bluetooth...",
    "imageUrl": "https://cf.shopee.com.br/file/br-11134207-820lw-mlen7c2lnx1i21",
    "ratingStar": "4.9",
    "priceDiscountRate": 78,
    "price": "29.89",
    "sales": 2208,
    "offerLink": "https://s.shopee.com.br/6AgbUXHGrC",
    "nicho": "Tech_e_Gadgets",
    "timestamp": 1774576697
  },
  {
    "productNameClean": "Massageador Elétrico Orbital Relax Spin Tone 110v",
    "imageUrl": "https://cf.shopee.com.br/file/br-11134207-81ztc-mj708m0q4mbm52",
    "ratingStar": "4.8",
    "priceDiscountRate": 50,
    "price": "72.9",
    "sales": 1078,
    "offerLink": "https://s.shopee.com.br/9ztK3jP1nu",
    "nicho": "Tech_e_Gadgets",
    "timestamp": 1774576829
  },
  {
    "productNameClean": "Pasta Térmica | Rise Mode | Frost 5g | 6...",
    "imageUrl": "https://cf.shopee.com.br/file/br-11134207-81z1k-mfa13emb3catc8",
    "ratingStar": "5",
    "priceDiscountRate": 21,
    "price": "26.9",
    "sales": 730,
    "offerLink": "https://s.shopee.com.br/4VYNW2DSv2",
    "nicho": "Tech_e_Gadgets",
    "timestamp": 1774577189
  },
  {
    "productNameClean": "Mouse Home Office Sem Fio - Bateria Interna Recarregável...",
    "imageUrl": "https://cf.shopee.com.br/file/br-11134207-81z1k-mhelddzuvu2tea",
    "ratingStar": "4.9",
    "priceDiscountRate": 40,
    "price": "21.9",
    "sales": 2569,
    "offerLink": "https://s.shopee.com.br/7KsYtgrMu7",
    "nicho": "Tech_e_Gadgets",
    "timestamp": 1774577581
  },
  {
    "productNameClean": "tablet não incluso Teclado BETTDOW para Samsung Tab S6 S7-S9FE...",
    "imageUrl": "https://cf.shopee.com.br/file/br-11134207-81zuh-ml4favk9v1tvf8",
    "ratingStar": "4.9",
    "priceDiscountRate": 61,
    "price": "389",
    "sales": 290,
    "offerLink": "https://s.shopee.com.br/3VfqL1Rk9V",
    "nicho": "Tech_e_Gadgets",
    "timestamp": 1774577909
  },
  {
    "productNameClean": "Carregador iPhone Original 20W Turbo iPhone 11 12 13 14...",
    "imageUrl": "https://cf.shopee.com.br/file/br-11134207-7r98o-mb5x2a3hh9cf81",
    "ratingStar": "4.8",
    "priceDiscountRate": 50,
    "price": "39.89",
    "sales": 6166,
    "offerLink": "https://s.shopee.com.br/20r2YcKARx",
    "nicho": "Tech_e_Gadgets",
    "timestamp": 1774578216
  },
  {
    "productNameClean": "Carregador Portátil Power Bank 10000mah com 3 Saídas v8 iphone...",
    "imageUrl": "https://cf.shopee.com.br/file/sg-11134201-824g2-meiubncsak1xcb",
    "ratingStar": "4.6",
    "priceDiscountRate": 65,
    "price": "27.99",
    "sales": 810,
    "offerLink": "https://s.shopee.com.br/1BHvZYgDWa",
    "nicho": "Tech_e_Gadgets",
    "timestamp": 1774578629
  }
]