[
  {
    "productNameClean": "Canivete Personalizado De bolso em Aço Inoxidavel Laser Clip Presilha...",
    "imageUrl": "https://cf.shopee.com.br/file/sg-11134201-82611-mjn9po4h47ieb0",
    "ratingStar": "4.9",
    "priceDiscountRate": 35,
    "price": "25.9",
    "sales": 310,
    "offerLink": "https://s.shopee.com.br/4Avaq9v5kF",
    "nicho": "Ferramentas",
    "timestamp": 1774778781
  },
  {
    "productNameClean": "Serra Mármore Madeira Piso Granito Cerâmica 1550W 45 Graus 110mm...",
    "imageUrl": "https://cf.shopee.com.br/file/br-11134207-7r98o-m1uyd1w2ckcoa3",
    "ratingStar": "4.7",
    "priceDiscountRate": 60,
    "price": "199.9",
    "sales": 621,
    "offerLink": "https://s.shopee.com.br/7VC2ohGIhX",
    "nicho": "Ferramentas",
    "timestamp": 1774779141
  },
  {
    "productNameClean": "Kit Limpeza Lavadora de Alta Pressão Potente Aplicador de Detergente...",
    "imageUrl": "https://cf.shopee.com.br/file/sg-11134201-7renr-m83hjet7zq9560",
    "ratingStar": "4.9",
    "priceDiscountRate": 10,
    "price": "629.99",
    "sales": 352,
    "offerLink": "https://s.shopee.com.br/2g6n4E2CQX",
    "nicho": "Ferramentas",
    "timestamp": 1774779501
  },
  {
    "productNameClean": "Parafusadeira Furadeira de Elétrica Sem Fio Impacto 48V Bateria 3...",
    "imageUrl": "https://cf.shopee.com.br/file/br-11134201-81z1k-mf2lhldku9l06c",
    "ratingStar": "4.9",
    "priceDiscountRate": 58,
    "price": "139",
    "sales": 2659,
    "offerLink": "https://s.shopee.com.br/1VupgUiwHs",
    "nicho": "Ferramentas",
    "timestamp": 1774779861
  },
  {
    "productNameClean": "Máquina de Solda Inversora IGBT Portátil MMA-250/300",
    "imageUrl": "https://cf.shopee.com.br/file/br-11134207-81zul-ml4qs68x5a8780",
    "ratingStar": "4.9",
    "priceDiscountRate": 54,
    "price": "238",
    "sales": 226,
    "offerLink": "https://s.shopee.com.br/2qQDHljw3t",
    "nicho": "Ferramentas",
    "timestamp": 1774780581
  },
  {
    "productNameClean": "Capa para copos térmicos Com Alça De Ombro Perfeita...",
    "imageUrl": "https://cf.shopee.com.br/file/br-11134207-81z1k-mg7n72zf37k7ad",
    "ratingStar": "4.9",
    "priceDiscountRate": 61,
    "price": "23.43",
    "sales": 403,
    "offerLink": "https://s.shopee.com.br/3B33gnGMH8",
    "nicho": "Ferramentas",
    "timestamp": 1774780941
  },
  {
    "productNameClean": "Cesto De Roupa Suja Dobrável Organizador 3 Compartimentos",
    "imageUrl": "https://cf.shopee.com.br/file/sg-11134201-7rce7-m6be8291hkuicf",
    "ratingStar": "4.9",
    "priceDiscountRate": 43,
    "price": "79.99",
    "sales": 609,
    "offerLink": "https://s.shopee.com.br/3qIkW4xelQ",
    "nicho": "Ferramentas",
    "timestamp": 1774782741
  },
  {
    "productNameClean": "Faca Alicate Universal Multiferramenta Dobráveis 6 em 1 com Kit...",
    "imageUrl": "https://cf.shopee.com.br/file/br-11134207-7r98o-m83b4chkummpb4",
    "ratingStar": "4.9",
    "priceDiscountRate": 66,
    "price": "47.96",
    "sales": 316,
    "offerLink": "https://s.shopee.com.br/2VnMw2aHt0",
    "nicho": "Ferramentas",
    "timestamp": 1774783101
  },
  {
    "productNameClean": "Lava Jato de Alta Pressão Pistola Portátil Lavadora Profissional Sem...",
    "imageUrl": "https://cf.shopee.com.br/file/br-11134207-7r98o-m4g8xokdbn05b3",
    "ratingStar": "4.7",
    "priceDiscountRate": 27,
    "price": "99.99",
    "sales": 1157,
    "offerLink": "https://s.shopee.com.br/808JUYnajl",
    "nicho": "Ferramentas",
    "timestamp": 1774783461
  },
  {
    "productNameClean": "【110V/220V】 Máquina Solda Inversora Profissional máquina de solda digital MMA-200/MMA-180/MMA-120~",
    "imageUrl": "https://cf.shopee.com.br/file/br-11134207-7r98o-m9jsgdbtkz0921",
    "ratingStar": "4.9",
    "priceDiscountRate": 51,
    "price": "255.8",
    "sales": 569,
    "offerLink": "https://s.shopee.com.br/6VJVicyks0",
    "nicho": "Ferramentas",
    "timestamp": 1774784181
  },
  {
    "productNameClean": "AUXOM Parafusadeira e Furadeira 21V 2 Baterias com 24 Bits...",
    "imageUrl": "https://cf.shopee.com.br/file/br-11134207-81ztc-mjxyakdpo6ip03",
    "ratingStar": "4.9",
    "priceDiscountRate": 76,
    "price": "99.98",
    "sales": 4191,
    "offerLink": "https://s.shopee.com.br/50Uhx6iMon",
    "nicho": "Ferramentas",
    "timestamp": 1774785261
  },
  {
    "productNameClean": "Aspirador de Pó 2 em 1 Limpeza Portátil Sem Fio...",
    "imageUrl": "https://cf.shopee.com.br/file/br-11134207-7r98o-lxyhg0rnv9ua8b",
    "ratingStar": "4.4",
    "priceDiscountRate": 70,
    "price": "79.99",
    "sales": 845,
    "offerLink": "https://s.shopee.com.br/5VQyYREVA6",
    "nicho": "Ferramentas",
    "timestamp": 1774785621
  },
  {
    "productNameClean": "AUXOM Parafusadeira e Furadeira 21V 2 Baterias com 24 Bits...",
    "imageUrl": "https://cf.shopee.com.br/file/br-11134207-81ztc-mjxyakdpo6ip03",
    "ratingStar": "4.9",
    "priceDiscountRate": 74,
    "price": "109",
    "sales": 4191,
    "offerLink": "https://s.shopee.com.br/7Kscl2ks7i",
    "nicho": "Ferramentas",
    "timestamp": 1774786699
  },
  {
    "productNameClean": "Robô Aspirador 3 em 1 Varre, Aspira e limpar...",
    "imageUrl": "https://cf.shopee.com.br/file/br-11134207-81z1k-mikpid5hf6ki16",
    "ratingStar": "4.3",
    "priceDiscountRate": 65,
    "price": "51.99",
    "sales": 2118,
    "offerLink": "https://s.shopee.com.br/6L05ZcMZre",
    "nicho": "Ferramentas",
    "timestamp": 1774787061
  },
  {
    "productNameClean": "Pulverizador Profissional de Espuma com Bomba 2L – Borrifador Spray...",
    "imageUrl": "https://cf.shopee.com.br/file/br-11134207-820l4-mmafg5ck3f9cc8",
    "ratingStar": "4.9",
    "priceDiscountRate": 42,
    "price": "34.99",
    "sales": 826,
    "offerLink": "https://s.shopee.com.br/BPSF6qC6E",
    "nicho": "Ferramentas",
    "timestamp": 1774787782
  },
  {
    "productNameClean": "Mochila Tática Impermeável Militar Reforçada 50L Preto Verde E Cáqui...",
    "imageUrl": "https://cf.shopee.com.br/file/br-11134207-820lx-mmdbrgf595ac9a",
    "ratingStar": "4.9",
    "priceDiscountRate": 47,
    "price": "106.79",
    "sales": 203,
    "offerLink": "https://s.shopee.com.br/20r6QtGhW2",
    "nicho": "Ferramentas",
    "timestamp": 1774788143
  },
  {
    "productNameClean": "Kit Ferro De Solda Soldar Soldador 60w + Estranho",
    "imageUrl": "https://cf.shopee.com.br/file/sg-11134201-7rfi8-m36ro5dvw6cn02",
    "ratingStar": "4.6",
    "priceDiscountRate": 15,
    "price": "25.5",
    "sales": 562,
    "offerLink": "https://s.shopee.com.br/2LTwpunOnz",
    "nicho": "Ferramentas",
    "timestamp": 1774788501
  },
  {
    "productNameClean": "Esmerilhadeira Lixadeira Angular Profissional 900w 115mm Com 3 Discos",
    "imageUrl": "https://cf.shopee.com.br/file/br-11134207-820m7-mlhotdf9q8sm99",
    "ratingStar": "4.9",
    "priceDiscountRate": 52,
    "price": "125",
    "sales": 454,
    "offerLink": "https://s.shopee.com.br/9AKGzi1Hqc",
    "nicho": "Ferramentas",
    "timestamp": 1774789581
  },
  {
    "productNameClean": "Máquina de Solda Inversor MIG-250 Sem Gás 3 em 1...",
    "imageUrl": "https://cf.shopee.com.br/file/br-11134207-81ztd-ml4f3n404l4xc7",
    "ratingStar": "4.8",
    "priceDiscountRate": 59,
    "price": "449",
    "sales": 1078,
    "offerLink": "https://s.shopee.com.br/6pwMEenevP",
    "nicho": "Ferramentas",
    "timestamp": 1774790661
  },
  {
    "productNameClean": "Kit Serra Adaptador de Serra Tico-Tico Elétrica para Furadeira...",
    "imageUrl": "https://cf.shopee.com.br/file/sg-11134201-7rdvn-mdqyys6nkcfw98",
    "ratingStar": "4.7",
    "priceDiscountRate": 57,
    "price": "25.78",
    "sales": 652,
    "offerLink": "https://s.shopee.com.br/9pZxoziF2S",
    "nicho": "Ferramentas",
    "timestamp": 1774791381
  },
  {
    "productNameClean": "Eletrodo Serralheiro 6013 VONDER Original 2,5mm 5KG",
    "imageUrl": "https://cf.shopee.com.br/file/br-11134207-81z1k-mhs7livd7vgid2",
    "ratingStar": "4.9",
    "priceDiscountRate": 30,
    "price": "69.9",
    "sales": 438,
    "offerLink": "https://s.shopee.com.br/4qBHtSCfDe",
    "nicho": "Ferramentas",
    "timestamp": 1774792821
  },
  {
    "productNameClean": "Aspirador de Pó Doméstico 3 em 1 Sem Fio Limpeza...",
    "imageUrl": "https://cf.shopee.com.br/file/br-11134207-81ztc-mkcjoatoypz734",
    "ratingStar": "4.5",
    "priceDiscountRate": 39,
    "price": "72.99",
    "sales": 380,
    "offerLink": "https://s.shopee.com.br/3B33vcsIwX",
    "nicho": "Ferramentas",
    "timestamp": 1774793901
  },
  {
    "productNameClean": "Cooktop de Indução Britânia Portátil Painel Touch BCTE10A",
    "imageUrl": "https://cf.shopee.com.br/file/sg-11134201-82608-mlyzbtxxuayr4a",
    "ratingStar": 4.9,
    "priceDiscountRate": 29,
    "price": 0,
    "sales": 209,
    "offerLink": "https://s.shopee.com.br/60NFHdlDdm",
    "nicho": "Cozinha",
    "timestamp": 1774792856
  },
  {
    "productNameClean": "Moto Esmeril de Bancada 6' 350W Bivolt Modelo 9727...",
    "imageUrl": "https://cf.shopee.com.br/file/sg-11134201-7rdvs-ly10yd5mgd5re3",
    "ratingStar": "4.9",
    "priceDiscountRate": 24,
    "price": "169.99",
    "sales": 606,
    "offerLink": "https://s.shopee.com.br/W2Il8egaD",
    "nicho": "Ferramentas",
    "timestamp": 1774794261
  },
  {
    "productNameClean": "Capa para copos térmicos Com Alça De Ombro Perfeita...",
    "imageUrl": "https://cf.shopee.com.br/file/br-11134207-81z1k-mg7n72zf37k7ad",
    "ratingStar": "4.9",
    "priceDiscountRate": 61,
    "price": "23.43",
    "sales": 403,
    "offerLink": "https://s.shopee.com.br/70FmWjRbTv",
    "nicho": "Ferramentas",
    "timestamp": 1774795699
  },
  {
    "productNameClean": "Extratora Higienizadora Portátil Borrifa Esfrega e Extrai Sujeira Colchão Sofá...",
    "imageUrl": "https://cf.shopee.com.br/file/sg-11134201-7rbn7-lqeu1vzxvsrqba",
    "ratingStar": "4.9",
    "priceDiscountRate": 24,
    "price": "683.7",
    "sales": 654,
    "offerLink": "https://s.shopee.com.br/1gEGBLJjjY",
    "nicho": "Ferramentas",
    "timestamp": 1774796061
  },
  {
    "productNameClean": "Cooktop de Indução Britânia Portátil Painel Touch BCTE10A",
    "imageUrl": "https://cf.shopee.com.br/file/sg-11134201-82608-mlyzbtxxuayr4a",
    "ratingStar": 4.9,
    "priceDiscountRate": 29,
    "price": 0,
    "sales": 209,
    "offerLink": "https://s.shopee.com.br/6fcw8ELZms",
    "nicho": "Cozinha",
    "timestamp": 1774795796
  },
  {
    "productNameClean": "Fatiador Profissional Multifuncional De Aço Inoxidável 16 Em 1...",
    "imageUrl": "https://cf.shopee.com.br/file/br-11134207-81z1k-mhjfa9ir0mbq21",
    "ratingStar": "4.8",
    "priceDiscountRate": 54,
    "price": "35.99",
    "sales": 9386,
    "offerLink": "https://s.shopee.com.br/1VupzRwjon",
    "nicho": "Cozinha",
    "timestamp": 1774796422
  },
  {
    "productNameClean": "2 Unidades Espanta Moscas Mosquitos Ventilador Portátil a Pilha Cozinha...",
    "imageUrl": "https://cf.shopee.com.br/file/br-11134207-820mc-mlc6b702rhmt88",
    "ratingStar": "4.8",
    "priceDiscountRate": 16,
    "price": "65.9",
    "sales": 225,
    "offerLink": "https://s.shopee.com.br/3fzKZqHv5U",
    "nicho": "Cozinha",
    "timestamp": 1774796781
  },
  {
    "productNameClean": "Cooktop de Indução Britânia Portátil Painel Touch BCTE10A",
    "imageUrl": "https://cf.shopee.com.br/file/sg-11134201-82608-mlyzbtxxuayr4a",
    "ratingStar": 4.9,
    "priceDiscountRate": 29,
    "price": 0,
    "sales": 209,
    "offerLink": "https://s.shopee.com.br/5Ao8MEH6Od",
    "nicho": "Cozinha",
    "timestamp": 1774796456
  },
  {
    "productNameClean": "Balança de Precisão Digital 10kg Para Cozinha Pesagem de Alimentos...",
    "imageUrl": "https://cf.shopee.com.br/file/br-11134207-81z1k-mh6f1iv2hlaffa",
    "ratingStar": "4.8",
    "priceDiscountRate": 56,
    "price": "21.99",
    "sales": 675,
    "offerLink": "https://s.shopee.com.br/4frrm5m0ll",
    "nicho": "Cozinha",
    "timestamp": 1774797141
  },
  {
    "productNameClean": "Kit Cozinha 19 Peças Silicone Antiaderente Facas Inox Madeira...",
    "imageUrl": "https://cf.shopee.com.br/file/br-11134207-7r98o-mdqhiro4jlix1d",
    "ratingStar": "4.8",
    "priceDiscountRate": 59,
    "price": "61.67",
    "sales": 2185,
    "offerLink": "https://s.shopee.com.br/1LbPoNWbFK",
    "nicho": "Cozinha",
    "timestamp": 1774797501
  },
  {
    "productNameClean": "Grelha Dupla folha Grande Churrasco Peixe Frango Linguiça Aço Multiuso...",
    "imageUrl": "https://cf.shopee.com.br/file/br-11134207-7r98o-m3c71eoafs9nf2",
    "ratingStar": "4.9",
    "priceDiscountRate": 53,
    "price": "32.99",
    "sales": 492,
    "offerLink": "https://s.shopee.com.br/50UiBWqbmy",
    "nicho": "Cozinha",
    "timestamp": 1774797861
  },
  {
    "productNameClean": "Chaleira Inox com Apito Ferve Rápido Fogão Gás Indução Elétrico",
    "imageUrl": "https://cf.shopee.com.br/file/br-11134207-81z1k-mfwhtbm9pqmff5",
    "ratingStar": "4.6",
    "priceDiscountRate": 55,
    "price": "26.99",
    "sales": 1407,
    "offerLink": "https://s.shopee.com.br/4qBI02x2Vw",
    "nicho": "Cozinha",
    "timestamp": 1774798581
  },
  {
    "productNameClean": "Panela De Pressão 4,5 Litros Antiaderente Teflon Com Tampa Externa...",
    "imageUrl": "https://cf.shopee.com.br/file/br-11134207-7r98o-m9068frjp1xe46",
    "ratingStar": "4.8",
    "priceDiscountRate": 35,
    "price": "149.9",
    "sales": 1401,
    "offerLink": "https://s.shopee.com.br/3B341Obcua",
    "nicho": "Cozinha",
    "timestamp": 1774798941
  },
  {
    "productNameClean": "Tritador de alimentos de 2 litros, carne e vegetais, processador...",
    "imageUrl": "https://cf.shopee.com.br/file/br-11134207-7r98o-md7343n3ec6q68",
    "ratingStar": "4.8",
    "priceDiscountRate": 65,
    "price": "69.95",
    "sales": 366,
    "offerLink": "https://s.shopee.com.br/4qBI1HafOX",
    "nicho": "Cozinha",
    "timestamp": 1774799661
  },
  {
    "productNameClean": "Cooktop de Indução Britânia Portátil Painel Touch BCTE10A",
    "imageUrl": "https://cf.shopee.com.br/file/sg-11134201-82608-mlyzbtxxuayr4a",
    "ratingStar": 4.9,
    "priceDiscountRate": 29,
    "price": 0,
    "sales": 209,
    "offerLink": "https://s.shopee.com.br/9KdhNFeThx",
    "nicho": "Cozinha",
    "timestamp": 1774799396
  },
  {
    "productNameClean": "Bule De Inox Para Café Cha 280/420/550ml Cafeteira Portátil Leiteira...",
    "imageUrl": "https://cf.shopee.com.br/file/br-11134207-7r98o-lwn8f2e5fhx2dd",
    "ratingStar": "4.7",
    "priceDiscountRate": 13,
    "price": "22.49",
    "sales": 1833,
    "offerLink": "https://s.shopee.com.br/6fcwDt7Nmc",
    "nicho": "Cozinha",
    "timestamp": 1774800741
  },
  {
    "productNameClean": "Cooktop de Indução Britânia Portátil Painel Touch BCTE10A",
    "imageUrl": "https://cf.shopee.com.br/file/sg-11134201-82608-mlyzbtxxuayr4a",
    "ratingStar": 4.9,
    "priceDiscountRate": 29,
    "price": 0,
    "sales": 209,
    "offerLink": "https://s.shopee.com.br/1LbPrIz5iv",
    "nicho": "Cozinha",
    "timestamp": 1774800056
  },
  {
    "productNameClean": "Máquina de Algodão Doce 220V Profissional – Ideal para Buffet...",
    "imageUrl": "https://cf.shopee.com.br/file/br-11134207-81z1k-mhizel1w0m4h9f",
    "ratingStar": "4.9",
    "priceDiscountRate": 20,
    "price": "876.89",
    "sales": 110,
    "offerLink": "https://s.shopee.com.br/20r6fix2wu",
    "nicho": "Cozinha",
    "timestamp": 1774801101
  },
  {
    "productNameClean": "Mini Liquidificador Portátil Shake 6 Laminas + Cabo USB",
    "imageUrl": "https://cf.shopee.com.br/file/br-11134207-7r98q-llmij8jid08q65",
    "ratingStar": "4.6",
    "priceDiscountRate": 68,
    "price": "25.99",
    "sales": 8221,
    "offerLink": "https://s.shopee.com.br/W2ItNaehB",
    "nicho": "Cozinha",
    "timestamp": 1774801461
  },
  {
    "productNameClean": "Mini Processador Triturador Sem Fio Elétrico 250ML De Alimentos...",
    "imageUrl": "https://cf.shopee.com.br/file/br-11134207-81ztc-mkaq8qcy4nwi2c",
    "ratingStar": "4.7",
    "priceDiscountRate": 52,
    "price": "22.99",
    "sales": 2703,
    "offerLink": "https://s.shopee.com.br/9AKHDibyQj",
    "nicho": "Cozinha",
    "timestamp": 1774801821
  },
  {
    "productNameClean": "Kit 19 Pçs Utensílios Cozinha Luxo Tábua Espátula Tesoura",
    "imageUrl": "https://cf.shopee.com.br/file/sg-11134201-7rdvj-lxsfo89qzo0w45",
    "ratingStar": "4.7",
    "priceDiscountRate": 50,
    "price": "54.95",
    "sales": 882,
    "offerLink": "https://s.shopee.com.br/4frrsGyYeX",
    "nicho": "Cozinha",
    "timestamp": 1774802541
  },
  {
    "productNameClean": "Kit 1/Kit 2 Pilhas Recarregáveis 9V 650mAh IIgenai - USB-C...",
    "imageUrl": "https://cf.shopee.com.br/file/br-11134207-81z1k-mghbjco3turr80",
    "ratingStar": "4.9",
    "priceDiscountRate": 49,
    "price": "35.99",
    "sales": 484,
    "offerLink": "https://s.shopee.com.br/2LTx6oDa55",
    "nicho": "Cozinha",
    "timestamp": 1774803279
  },
  {
    "productNameClean": "Cooktop de Indução Britânia Portátil Painel Touch BCTE10A",
    "imageUrl": "https://cf.shopee.com.br/file/sg-11134201-82608-mlyzbtxxuayr4a",
    "ratingStar": 4.9,
    "priceDiscountRate": 29,
    "price": 0,
    "sales": 209,
    "offerLink": "https://s.shopee.com.br/8KlAFXBc6l",
    "nicho": "Cozinha",
    "timestamp": 1774802996
  },
  {
    "productNameClean": "Frigideira Panquequeira Antiaderente 22Cm Nacional",
    "imageUrl": "https://cf.shopee.com.br/file/br-11134207-81z1k-mgi3y2770phce7",
    "ratingStar": "4.9",
    "priceDiscountRate": 35,
    "price": "24",
    "sales": 1784,
    "offerLink": "https://s.shopee.com.br/5q3pHecYTy",
    "nicho": "Cozinha",
    "timestamp": 1774803622
  },
  {
    "productNameClean": "1/2Rack de pratos em camadas sobre a pia Rack...",
    "imageUrl": "https://cf.shopee.com.br/file/br-11134207-81z1k-mggb8luuhq0w92",
    "ratingStar": "4.8",
    "priceDiscountRate": 81,
    "price": "93.99",
    "sales": 847,
    "offerLink": "https://s.shopee.com.br/5L7Yh97c6V",
    "nicho": "Cozinha",
    "timestamp": 1774803981
  },
  {
    "productNameClean": "Máquina de Lavar Twin Tub Praxis 10kg 2 em 1...",
    "imageUrl": "https://cf.shopee.com.br/file/sg-11134201-824hf-mfobvevqv4soc6",
    "ratingStar": 4.9,
    "priceDiscountRate": 25,
    "price": 0,
    "sales": 372,
    "offerLink": "https://s.shopee.com.br/4VYRhFG1PL",
    "nicho": "Casa",
    "timestamp": 1774803656
  },
  {
    "productNameClean": "Nova Atualização！Aspirador e Soprador Portátil 5 em 1 - Alta...",
    "imageUrl": "https://cf.shopee.com.br/file/sg-11134201-824hm-mfp89l0bhmob66",
    "ratingStar": "4.4",
    "priceDiscountRate": 34,
    "price": "26.69",
    "sales": 5108,
    "offerLink": "https://s.shopee.com.br/AUperv4MR3",
    "nicho": "Casa",
    "timestamp": 1774805098
  },
  {
    "productNameClean": "Muro Inglês Jardim Vertical 2,00 x 0,50 cm Metros Hera...",
    "imageUrl": "https://cf.shopee.com.br/file/br-11134207-7r98o-mcgfd5ii6ha979",
    "ratingStar": "4.9",
    "priceDiscountRate": 65,
    "price": "41.9",
    "sales": 285,
    "offerLink": "https://s.shopee.com.br/BPSZLG0fx",
    "nicho": "Casa",
    "timestamp": 1774805458
  },
  {
    "productNameClean": "Maçanetas Par - Alta Qualidade, Super Resistente, Universal Interna...",
    "imageUrl": "https://cf.shopee.com.br/file/br-11134207-81z1k-mhg6oyss8wsm0e",
    "ratingStar": "4.9",
    "priceDiscountRate": 66,
    "price": "21.25",
    "sales": 458,
    "offerLink": "https://s.shopee.com.br/2VnNM2f1eT",
    "nicho": "Casa",
    "timestamp": 1774805820
  },
  {
    "productNameClean": "Caixa grande de armazenamento com zíper para roupas e cobertores...",
    "imageUrl": "https://cf.shopee.com.br/file/br-11134207-7r98o-m7hql5rs26a4a4",
    "ratingStar": "4.8",
    "priceDiscountRate": 76,
    "price": "28.9",
    "sales": 1726,
    "offerLink": "https://s.shopee.com.br/9ztOIEkN8N",
    "nicho": "Casa",
    "timestamp": 1774806178
  },
  {
    "productNameClean": "Cortina Blackout PVC Corta 100% a Luz 2,80 m x...",
    "imageUrl": "https://cf.shopee.com.br/file/br-11134207-81z1k-mee7oe27u51fcd",
    "ratingStar": "4.7",
    "priceDiscountRate": 20,
    "price": "32.98",
    "sales": 2670,
    "offerLink": "https://s.shopee.com.br/6fcwKWUY3o",
    "nicho": "Casa",
    "timestamp": 1774806538
  },
  {
    "productNameClean": "Escrivaninha MAXI para Escritório Home Office com Porta e Nicho...",
    "imageUrl": "https://cf.shopee.com.br/file/br-11134207-81ztc-mk2txsadafwj96",
    "ratingStar": "4.7",
    "priceDiscountRate": 40,
    "price": "208.6",
    "sales": 1497,
    "offerLink": "https://s.shopee.com.br/4VYRkxAyBO",
    "nicho": "Casa",
    "timestamp": 1774806898
  },
  {
    "productNameClean": "Ventilador de Teto LED 60W 80W Lâmpada E27 Controle Remoto...",
    "imageUrl": "https://cf.shopee.com.br/file/cn-11134207-820l4-mkixsca7ixaacf",
    "ratingStar": 4.8,
    "priceDiscountRate": 60,
    "price": 0,
    "sales": 2417,
    "offerLink": "https://s.shopee.com.br/6pwMWqgi1Y",
    "nicho": "Casa",
    "timestamp": 1774806553
  },
  {
    "productNameClean": "Umidificador De Ar Difusor Aromatizador Cor Madeira Escuro USB Ultrassônico...",
    "imageUrl": "https://cf.shopee.com.br/file/br-11134207-7r98o-mblub1hr63js1c",
    "ratingStar": "4.8",
    "priceDiscountRate": 85,
    "price": "20.79",
    "sales": 1497,
    "offerLink": "https://s.shopee.com.br/8phQvKSALY",
    "nicho": "Casa",
    "timestamp": 1774807258
  },
  {
    "productNameClean": "Máquina de Lavar Twin Tub Praxis 10kg 2 em 1...",
    "imageUrl": "https://cf.shopee.com.br/file/sg-11134201-824hf-mfobvevqv4soc6",
    "ratingStar": 4.9,
    "priceDiscountRate": 25,
    "price": 0,
    "sales": 372,
    "offerLink": "https://s.shopee.com.br/AUpeuLIqDm",
    "nicho": "Casa",
    "timestamp": 1774807214
  },
  {
    "productNameClean": "Kit Tapete Banheiro Microfibra Bolinha com 3 Peças Antiderrapante Bolinha...",
    "imageUrl": "https://cf.shopee.com.br/file/br-11134207-81z1k-mf9og8vxnqpw10",
    "ratingStar": "4.9",
    "priceDiscountRate": 53,
    "price": "38.99",
    "sales": 2023,
    "offerLink": "https://s.shopee.com.br/30jdz1MTdZ",
    "nicho": "Casa",
    "timestamp": 1774807618
  },
  {
    "productNameClean": "Kit Travesseiro Pluma de Ganso Confortavel e Macio Antiacaro 70x50cm",
    "imageUrl": "https://cf.shopee.com.br/file/br-11134207-7r98o-m6nf0kpaoje8a6",
    "ratingStar": "4.7",
    "priceDiscountRate": 67,
    "price": "30.9",
    "sales": 20220,
    "offerLink": "https://s.shopee.com.br/9ztOKi1Q3i",
    "nicho": "Casa",
    "timestamp": 1774808338
  },
  {
    "productNameClean": "Fechadura de Porta de Casa Stilo Residencial Externa Sala Cozinha...",
    "imageUrl": "https://cf.shopee.com.br/file/br-11134207-7r98o-mc883jlw3j6ze9",
    "ratingStar": "4.9",
    "priceDiscountRate": 22,
    "price": "44.9",
    "sales": 646,
    "offerLink": "https://s.shopee.com.br/4AvbPdZ9Tm",
    "nicho": "Casa",
    "timestamp": 1774809778
  },
  {
    "productNameClean": "Agua Perfumada Aromatizador de Ambiente e Home Spray para Tecidos...",
    "imageUrl": "https://cf.shopee.com.br/file/br-11134207-81z1k-mgi0u2rf6jnp9b",
    "ratingStar": "4.9",
    "priceDiscountRate": 51,
    "price": "21.99",
    "sales": 199,
    "offerLink": "https://s.shopee.com.br/20r6qTnCH0",
    "nicho": "Casa",
    "timestamp": 1774810498
  },
  {
    "productNameClean": "Cortina Blackout premium de 6,00 x 2,80 Diversas Cores...",
    "imageUrl": "https://cf.shopee.com.br/file/br-11134207-7r98o-m6mkst7i0k7bad",
    "ratingStar": "4.9",
    "priceDiscountRate": 27,
    "price": "51.99",
    "sales": 6054,
    "offerLink": "https://s.shopee.com.br/1LbQ3fNhc9",
    "nicho": "Casa",
    "timestamp": 1774810858
  },
  {
    "productNameClean": "Secador Roupas Portátil Eletrico Secador Suspenso Cortina JH",
    "imageUrl": "https://cf.shopee.com.br/file/sg-11134201-824id-merhk8li10qsfd",
    "ratingStar": 4.8,
    "priceDiscountRate": 35,
    "price": 0,
    "sales": 85,
    "offerLink": "https://s.shopee.com.br/9pZyBFsMDt",
    "nicho": "Casa",
    "timestamp": 1774810828
  },
  {
    "productNameClean": "Ferro de Passar Onistek ON-PR905 Alta Temperatura para Tecidos...",
    "imageUrl": "https://cf.shopee.com.br/file/br-11134207-81zu8-mklc47o0ijnkb7",
    "ratingStar": "4.9",
    "priceDiscountRate": 75,
    "price": "58.9",
    "sales": 461,
    "offerLink": "https://s.shopee.com.br/AUpeyvN30i",
    "nicho": "Casa",
    "timestamp": 1774811218
  },
  {
    "productNameClean": "Mesa Dobravel Retratil de Parede Suspensa Borda Redonda 90Cm 100Cm...",
    "imageUrl": "https://cf.shopee.com.br/file/br-11134207-7r98o-m927ywvhqn7m5f",
    "ratingStar": "4.9",
    "priceDiscountRate": 36,
    "price": "77",
    "sales": 2065,
    "offerLink": "https://s.shopee.com.br/4LF1ePqBPX",
    "nicho": "Casa",
    "timestamp": 1774811938
  }
]